{
    "autokey": [
        [
            "2/07",
            "[討論] 我要幫柯文哲的位置說…"
        ],
        [
            "2/07",
            "[討論] 念念無明~有沒有政治網…"
        ],
        [
            "2/07",
            "[創作] 涼涼"
        ],
        [
            "2/07",
            "[創作] 眼底星空   演唱:李聖…"
        ],
        [
            "2/07",
            "[討論] 移民署的電腦系統應該…"
        ]
    ],
    "ilw4e": [
        [
            "2/07",
            "R: [討論] 小智真的應該被開除吧"
        ],
        [
            "2/07",
            "R: [討論] 藍白粉為什麼不滾出台…"
        ],
        [
            "2/07",
            "R: [討論] 難怪台女說不要柯粉"
        ],
        [
            "2/07",
            "[討論] 金門開了先例其它縣市…"
        ],
        [
            "2/07",
            "R: [轉錄] 沃草：煩死了，好想要…"
        ]
    ],
    "josh79103": [
        [
            "2/07",
            "[討論] 小智應該選總統了吧？"
        ]
    ],
    "leopika": [
        [
            "2/07",
            "[黑特] 民眾黨里長闖紅燈,叫警…"
        ]
    ],
    "goatcheese": [
        [
            "2/07",
            "[討論] 林智堅選總統副總統他…"
        ],
        [
            "2/07",
            "[討論] 基進黨的志工平常都在…"
        ],
        [
            "2/07",
            "[討論] 志工事件基進黨可能會…"
        ],
        [
            "2/07",
            "[討論] 陳柏惟肇事逃逸幫喊加…"
        ],
        [
            "2/07",
            "[討論] 性別發展部主任吳欣岱…"
        ]
    ],
    "m54k600ive80": [
        [
            "2/07",
            "R: [討論] 檢調搜索前會先通知當…"
        ]
    ],
    "Behind4": [
        [
            "2/07",
            "[討論] 土耳其強震 台灣人 又…"
        ],
        [
            "2/07",
            "[討論] 林智堅總統 打破學歷障壁"
        ],
        [
            "2/07",
            "[討論] 什麼時候 要廢除原住民…"
        ],
        [
            "2/07",
            "[討論] 被騙砲的 都是藍白4%女…"
        ]
    ],
    "ivorysoap": [
        [
            "2/07",
            "R: [討論] 小智真的應該被開除吧"
        ],
        [
            "2/07",
            "R: [轉錄] 翁達瑞：竹管局終將付…"
        ]
    ],
    "AMDMARSHAL": [
        [
            "2/07",
            "[黑特] 小智拿的是阿扁劇本吧"
        ]
    ],
    "yoyoflag": [
        [
            "2/07",
            "R: [討論] 小智真的應該被開除吧"
        ],
        [
            "2/07",
            "[討論] 食糞的留言者 484機器人?"
        ],
        [
            "2/07",
            "R: [討論] 為什麼八卦版沒什麼人…"
        ],
        [
            "2/07",
            "[討論] 中國氣球被打爆 到底在…"
        ],
        [
            "2/07",
            "[討論] 賴清德何時會對小英男…"
        ]
    ],
    "whitefox": [
        [
            "2/07",
            "[新聞] 地主不願開挖 桃園百戶…"
        ],
        [
            "2/07",
            "[新聞] 八里汙水廠移交拍板5年…"
        ]
    ],
    "traman": [
        [
            "2/07",
            "R: [討論] 小智真的應該被開除吧"
        ]
    ],
    "EVEA": [
        [
            "2/07",
            "[討論] 民進黨要成立個資保護…"
        ],
        [
            "2/07",
            "[討論] 中國氣球飛到台灣- 鄭…"
        ]
    ],
    "Gavatzky": [
        [
            "2/07",
            "[討論] 隔壁版：高雄燈會像是…"
        ],
        [
            "2/07",
            "R: [黑特] 蔡政府做的不好為何賴…"
        ],
        [
            "2/07",
            "[討論] 我幹 基進小綠一邊選舉…"
        ],
        [
            "2/07",
            "[討論] sex版女綠粉：想加入基…"
        ],
        [
            "2/07",
            "R: [討論] 至少柯文哲跟黃珊珊可…"
        ]
    ],
    "WiserWilly": [
        [
            "2/07",
            "[討論] 這樣民進黨學乖了沒"
        ]
    ],
    "awex": [
        [
            "2/07",
            "R: [討論] 小智真的應該被開除吧"
        ],
        [
            "2/07",
            "R: [討論] 黃光芹: 郭台銘是可以…"
        ]
    ],
    "nightwing": [
        [
            "2/07",
            "[新聞] 趕在議會撐「保護傘」…"
        ],
        [
            "2/07",
            "[新聞] 台南議長賄選案！檢調…"
        ],
        [
            "2/07",
            "[新聞] 台南議長涉賄案　民進…"
        ]
    ],
    "maxknife": [
        [
            "2/07",
            "[討論] 賴清德當黨主席後有改…"
        ]
    ],
    "minjindon": [
        [
            "2/07",
            "[黑特] 小智市長和阿扁總統一…"
        ]
    ],
    "drea": [
        [
            "2/07",
            "[新聞] 台中捷運藍線坪頂站要…"
        ],
        [
            "2/07",
            "[討論] 為何台中市政府要在藍…"
        ]
    ],
    "kuninaka": [
        [
            "2/07",
            "[新聞] 模擬中美若開戰？　美…"
        ],
        [
            "2/07",
            "[新聞] 中國國台辦主任宋濤：…"
        ],
        [
            "2/07",
            "[新聞] 義務役來了 志願役招募…"
        ],
        [
            "2/07",
            "[討論] 大家怎麼看境外勢力翁…"
        ],
        [
            "2/07",
            "[討論] 至少柯文哲跟黃珊珊可…"
        ]
    ],
    "andy199113": [
        [
            "2/07",
            "R: [討論] 民進黨要成立個資保護…"
        ],
        [
            "2/07",
            "R: [新聞] 管中閔憶台大校長遴選…"
        ]
    ],
    "blargelp": [
        [
            "2/07",
            "R: [討論] 黃光芹: 郭台銘是可以…"
        ],
        [
            "2/07",
            "[討論] 今年服務業薪資必然上漲"
        ]
    ],
    "ppp123": [
        [
            "2/07",
            "[黑特] 賴清德敢開除小智 我就…"
        ],
        [
            "2/07",
            "[討論] 高虹安上任這麼久 新竹…"
        ]
    ],
    "saufu08": [
        [
            "2/07",
            "[討論] 你對2024新總統有什麼…"
        ],
        [
            "2/07",
            "[討論] 當時勝文跟守中怎麼會…"
        ]
    ],
    "tony900735": [
        [
            "2/07",
            "[轉錄] 台北市動保處動物之家…"
        ],
        [
            "2/07",
            "[討論] 侯侯奏戴擠，但新北捷…"
        ]
    ],
    "urban": [
        [
            "2/07",
            "R: [討論] 會被側翼網軍帶風向的…"
        ]
    ],
    "geordie": [
        [
            "2/07",
            "[黑特] 瑞士訪台團干涉中國內政"
        ],
        [
            "2/07",
            "R: [新聞] 氣球事件 中國：考驗美…"
        ],
        [
            "2/07",
            "[新聞] 施明德：金馬非軍事區…"
        ]
    ],
    "stevencool": [
        [
            "2/07",
            "R: [討論] 為何台中市政府要在藍…"
        ],
        [
            "2/07",
            "[討論] 王金平在政壇還有影響…"
        ],
        [
            "2/07",
            "[轉錄] 柯建銘FB:請問朱立倫，…"
        ],
        [
            "2/07",
            "[討論] 柯建銘曾恐嚇管中閔：…"
        ]
    ],
    "jimlexus": [
        [
            "2/07",
            "[討論] 開除林智堅，有助於民…"
        ]
    ],
    "liseeker": [
        [
            "2/07",
            "R: [討論] 會被側翼網軍帶風向的…"
        ]
    ],
    "myIDis7": [
        [
            "2/07",
            "R: [新聞] 燈會開幕被換位子淪邊…"
        ]
    ],
    "Yaomini": [
        [
            "2/07",
            "[新聞] 同黨秦慧珠嗆「喜歡亂…"
        ]
    ],
    "bengowa": [
        [
            "2/07",
            "[新聞] 直擊！行政院閣員蹺班…"
        ]
    ],
    "Braum5566": [
        [
            "2/07",
            "[新聞] 民進黨台中立委選舉「…"
        ],
        [
            "2/07",
            "[新聞] 遭控劈腿多位女性 陳玄…"
        ]
    ],
    "assxass": [
        [
            "2/07",
            "[討論] 專訪國民黨台北市主委 …"
        ]
    ],
    "purplvampire": [
        [
            "2/07",
            "R: [討論] 民進黨要成立個資保護…"
        ],
        [
            "2/07",
            "[討論] 蕭美琴連花蓮都選不上…"
        ],
        [
            "2/07",
            "[討論] 難怪台女說不要柯粉"
        ],
        [
            "2/07",
            "[討論] 那些整天扯鍾東錦的塔…"
        ],
        [
            "2/07",
            "[討論] 對比柯文哲的大氣,就覺…"
        ]
    ],
    "abc9bitedi": [
        [
            "2/07",
            "[討論] 怎麼內閣換了人 政黑常…"
        ]
    ],
    "powderzhon": [
        [
            "2/07",
            "[新聞] 【台南正副議長涉賄】…"
        ],
        [
            "2/07",
            "[討論] 台南議長被搜出200萬 2…"
        ],
        [
            "2/07",
            "[討論] 為什麼塔綠班網路預算…"
        ],
        [
            "2/07",
            "[討論] 陳玄曄酒駕判3個月 變…"
        ]
    ],
    "Aidrux": [
        [
            "2/07",
            "[討論] 陳建仁發文開酸猴猴做…"
        ],
        [
            "2/07",
            "[討論] 中國華為要有25萬人失…"
        ],
        [
            "2/07",
            "[討論] 基進當初拒絕提名陳玄曄"
        ]
    ],
    "kymco9999": [
        [
            "2/07",
            "[黑特] 蔡政府做的不好為何賴…"
        ]
    ],
    "giorno78": [
        [
            "2/07",
            "[討論] AI量刑系統已啟用 林智…"
        ],
        [
            "2/07",
            "[討論] 中國承認拉丁美洲上空…"
        ],
        [
            "2/07",
            "[討論] 明明是「俠道」 為何要…"
        ],
        [
            "2/07",
            "[討論] 民間資安漏洞頻傳 數位…"
        ],
        [
            "2/07",
            "[討論] 民生蛋又要漲3元 台灣…"
        ]
    ],
    "keel90135": [
        [
            "2/07",
            "[轉錄] 翁達瑞：竹管局終將付…"
        ],
        [
            "2/07",
            "[新聞] 「國民黨要感謝林智堅…"
        ],
        [
            "2/07",
            "[討論] 側翼現在最討厭的人是…"
        ]
    ],
    "moshenisshit": [
        [
            "2/07",
            "R: [黑特] 蔡政府做的不好為何賴…"
        ],
        [
            "2/07",
            "R: [討論] 為何台中市政府要在藍…"
        ]
    ],
    "stu60001": [
        [
            "2/07",
            "[討論] 真的有深綠費粉？"
        ]
    ],
    "docose": [
        [
            "2/07",
            "R: [討論] 民進黨要成立個資保護…"
        ]
    ],
    "lpbrother": [
        [
            "2/07",
            "[新聞] 陳水扁談綠總統人選 賴…"
        ],
        [
            "2/07",
            "R: [新聞] 陳水扁：陳建仁受邀入…"
        ],
        [
            "2/07",
            "[討論] 為啥馬英九都不接受訪…"
        ],
        [
            "2/07",
            "[新聞] 敘利亞叛軍控制區至少7…"
        ]
    ],
    "shiaubai": [
        [
            "2/07",
            "[討論] 郭王配會不會是最大公…"
        ]
    ],
    "Pietro": [
        [
            "2/07",
            "[轉錄] 民眾黨：我們不訴諸仇…"
        ],
        [
            "2/07",
            "[新聞]燈會柯文哲站最邊邊  卓…"
        ]
    ],
    "seabox": [
        [
            "2/07",
            "[黑特] 幹你娘 還有人不認九二…"
        ],
        [
            "2/07",
            "[討論] 覺青生活很淫亂嗎"
        ],
        [
            "2/07",
            "R: [討論] 徐巧芯對敵國政權的見解"
        ],
        [
            "2/07",
            "[討論] 國民黨就是桃色糾紛少 …"
        ],
        [
            "2/07",
            "[討論] 塔綠班都怎麼跟炮友調…"
        ]
    ],
    "Matz": [
        [
            "2/07",
            "[討論] peggy這次怎麼不發文啊？"
        ]
    ],
    "songgood": [
        [
            "2/07",
            "[討論] 小智是戰犯 但是主要戰…"
        ]
    ],
    "goldsingle": [
        [
            "2/07",
            "R: [討論] 民進黨要成立個資保護…"
        ]
    ],
    "jeanvanjohn": [
        [
            "2/07",
            "R: [新聞] 黑道未必叛國！沈伯洋…"
        ],
        [
            "2/07",
            "R: [討論] 會被側翼網軍帶風向的…"
        ],
        [
            "2/07",
            "[討論] 覺得眷村老人是\"奇行種…"
        ],
        [
            "2/07",
            "R: [討論] 怎麼有勇氣中出六個女人"
        ],
        [
            "2/07",
            "R: [新聞] 台大副教授駕車遇球棒…"
        ]
    ],
    "KingFelix": [
        [
            "2/07",
            "R: [黑特] 蔡政府做的不好為何賴…"
        ]
    ],
    "node1": [
        [
            "2/07",
            "[討論] 兩岸開展后若金門投降…"
        ]
    ],
    "m82": [
        [
            "2/07",
            "R: [新聞] 275萬劑BNT將銷毀 指揮…"
        ]
    ],
    "didder": [
        [
            "2/07",
            "[新聞] 王世堅爆林智堅唯一活…"
        ]
    ],
    "KONAMI": [
        [
            "2/07",
            "R: [黑特] 蔡政府做的不好為何賴…"
        ]
    ],
    "Dontco": [
        [
            "2/07",
            "[討論] 口罩達人 moslaa 請進"
        ]
    ],
    "yangzy": [
        [
            "2/07",
            "[討論] 你知道林智堅為什麼不…"
        ],
        [
            "2/07",
            "R: [新聞] 施明德：金馬非軍事區…"
        ],
        [
            "2/07",
            "[討論] 你信佛敢說你沒舍利子…"
        ]
    ],
    "scropio1190": [
        [
            "2/07",
            "[討論] 邱ZZ 150萬元交保沒人…"
        ]
    ],
    "BIA": [
        [
            "2/07",
            "[討論] 陳柏維堂哥劈腿的事情 …"
        ]
    ],
    "LeeSeDol": [
        [
            "2/07",
            "[新聞] 陳玄曄遭控渣男劈腿騙…"
        ],
        [
            "2/07",
            "[新聞] 朱立倫：從連戰開始國…"
        ],
        [
            "2/07",
            "[新聞] 民進黨堅持台獨又要和…"
        ],
        [
            "2/07",
            "[討論] 民眾黨中央：台灣要竭…"
        ]
    ],
    "abscented": [
        [
            "2/07",
            "[黑特] 一樣都是八年"
        ]
    ],
    "bightv42257": [
        [
            "2/07",
            "[討論] 中共是不是被美國耍了？"
        ]
    ],
    "satricky": [
        [
            "2/07",
            "[討論] 黃偉哲現在可為賴神做…"
        ]
    ],
    "albert820423": [
        [
            "2/07",
            "[討論] 民進黨會挺莉到底嗎"
        ],
        [
            "2/07",
            "R: [討論] 陳其邁為什麼要去蹭星…"
        ],
        [
            "2/07",
            "[討論] 有人還記得金美齡這個…"
        ]
    ],
    "snh48spush": [
        [
            "2/07",
            "[討論] 多數台派是不是典型的…"
        ]
    ],
    "chliu6686": [
        [
            "2/07",
            "R: [黑特] 幹你娘 還有人不認九二…"
        ]
    ],
    "krit1009": [
        [
            "2/07",
            "[討論] 運安會的主委那麼爽喔？"
        ]
    ],
    "McCain": [
        [
            "2/07",
            "[討論] 羅智強為何要這樣到處…"
        ]
    ],
    "sea130281": [
        [
            "2/07",
            "[討論] 翁達瑞是怎麼崛起的？"
        ],
        [
            "2/07",
            "[討論] 仍然在強力支持小智的…"
        ],
        [
            "2/07",
            "[討論] 台大的訴願呢?????"
        ]
    ],
    "peter308": [
        [
            "2/07",
            "[討論] 陸客已經進來了嗎??"
        ],
        [
            "2/07",
            "[討論] 民進黨要贏的唯一辦法!"
        ]
    ],
    "icrose": [
        [
            "2/07",
            "R: [討論] 中共是不是被美國耍了？"
        ],
        [
            "2/07",
            "R: [討論] 中國華為要有25萬人失…"
        ],
        [
            "2/07",
            "R: [轉錄] 重磅出擊！美參議員提…"
        ],
        [
            "2/07",
            "R: [新聞] 金門縣議會2次級團體成…"
        ],
        [
            "2/07",
            "R: [討論] 側翼現在最討厭的人是…"
        ]
    ],
    "jason486": [
        [
            "2/07",
            "[轉錄] 杜奕瑾FB:溫水煮白兔 …"
        ],
        [
            "2/07",
            "[黑特] 堂哥陳玄燁:邊棒賽邊回"
        ],
        [
            "2/07",
            "[新聞] 無懼陳柏惟強逼提名 台…"
        ]
    ],
    "Taiwan007": [
        [
            "2/07",
            "[討論] 高虹安跟邱莉莉的事件…"
        ],
        [
            "2/07",
            "[討論] 侯友宜內心真的會動念…"
        ]
    ],
    "you1111": [
        [
            "2/07",
            "[討論] 吳欣岱戴墨鏡算美女嗎？"
        ],
        [
            "2/07",
            "[討論] 范雲跟林穎孟會出來譴…"
        ]
    ],
    "akiranon": [
        [
            "2/07",
            "[討論] 陳其邁為什麼要去蹭星…"
        ],
        [
            "2/07",
            "[討論] 文英：愛台灣？愛你的…"
        ],
        [
            "2/07",
            "[討論] 幼稚園正名為幼兒園？"
        ]
    ],
    "jacklyl": [
        [
            "2/07",
            "[討論] 藍白粉為什麼不滾出台…"
        ],
        [
            "2/07",
            "[討論] 藍白粉今天KPI是洗基進…"
        ],
        [
            "2/07",
            "[討論] 可惡的綠共害我生活不…"
        ]
    ],
    "chirex": [
        [
            "2/07",
            "R: [新聞] 陳玄曄遭控渣男劈腿騙…"
        ],
        [
            "2/07",
            "[新聞] 【閣員蹺班爽泡湯1】新…"
        ],
        [
            "2/07",
            "[黑特] 吃個滷肉飯體會到何謂…"
        ],
        [
            "2/07",
            "[新聞] 歧視？美中學竟在黑人…"
        ]
    ],
    "hong888": [
        [
            "2/07",
            "[討論] 朝野共好真的來臨?"
        ]
    ],
    "kabor": [
        [
            "2/07",
            "[新聞] 《獨家》離譜！國安高…"
        ],
        [
            "2/07",
            "[新聞] 管中閔憶台大校長遴選…"
        ]
    ],
    "ddaaemon": [
        [
            "2/07",
            "R: [討論] 翁達瑞是怎麼崛起的？"
        ]
    ],
    "starport": [
        [
            "2/07",
            "[新聞] 國安高層被爆機場咆哮…"
        ]
    ],
    "louiswei1986": [
        [
            "2/07",
            "R: [新聞] 國安高層被爆機場咆哮…"
        ]
    ],
    "generalfungi": [
        [
            "2/07",
            "[黑特] 找到支持朱主席的理由…"
        ]
    ],
    "Friend5566": [
        [
            "2/07",
            "[討論] 為什麼youtube柯粉比例…"
        ],
        [
            "2/07",
            "[討論] 陳柏惟跟陳玄曄長得好像"
        ],
        [
            "2/07",
            "[討論] 為何新竹市處長婚外情…"
        ],
        [
            "2/07",
            "[討論] 很多志工都把政治人物…"
        ]
    ],
    "pkpkc": [
        [
            "2/07",
            "[討論] 所以李登輝跟王金平是…"
        ]
    ],
    "johnny9667": [
        [
            "2/07",
            "R: [新聞] 國安高層被爆機場咆哮…"
        ]
    ],
    "hittler": [
        [
            "2/07",
            "[討論] 挪威和冰島議員何時訪…"
        ]
    ],
    "zeuswell": [
        [
            "2/07",
            "[討論] 台灣政治太黑暗，決定…"
        ]
    ],
    "BleedWang": [
        [
            "2/07",
            "R: [討論] 有人還記得金美齡這個…"
        ]
    ],
    "palindromes": [
        [
            "2/07",
            "[討論] 聽王力宏新歌看林智堅…"
        ]
    ],
    "CPer": [
        [
            "2/07",
            "[討論] 党還是需要翁達瑞這類…"
        ]
    ],
    "jetalpha": [
        [
            "2/07",
            "[轉錄] 重磅出擊！美參議員提…"
        ],
        [
            "2/07",
            "[黑特] 新加坡 2023/02/07 疫…"
        ]
    ],
    "Supasizeit": [
        [
            "2/07",
            "[黑特] 高虹安見日本知事用會…"
        ],
        [
            "2/07",
            "[黑特] 12億棒球場真的很便宜"
        ],
        [
            "2/07",
            "R: [討論] 論金門非軍事區對台百…"
        ]
    ],
    "jojoway": [
        [
            "2/07",
            "[討論] 笑死 羅智強連挑戰閃尿…"
        ],
        [
            "2/07",
            "R: [討論] 羅智強為何要這樣到處…"
        ]
    ],
    "Mazda6680": [
        [
            "2/07",
            "R: [新聞] 同黨秦慧珠嗆「喜歡亂…"
        ],
        [
            "2/07",
            "R: [討論] 侯友宜內心真的會動念…"
        ]
    ],
    "l81311i": [
        [
            "2/07",
            "[討論] 金門非軍事區好不好？"
        ]
    ],
    "omanorboyo": [
        [
            "2/07",
            "[討論] 猴猴做代誌選總統要請…"
        ],
        [
            "2/07",
            "[討論] 陳柏惟為啥要替堂哥私了"
        ]
    ],
    "gs1": [
        [
            "2/07",
            "[創作] 郭台銘的勝選票源在哪…"
        ]
    ],
    "ll6a": [
        [
            "2/07",
            "[討論] 翁瑞達專業是什麼"
        ],
        [
            "2/07",
            "[討論] 女森是不是很容易被綠…"
        ]
    ],
    "DDDDRR": [
        [
            "2/07",
            "[新聞] 雞蛋傳將漲3元？陳吉仲…"
        ],
        [
            "2/07",
            "[新聞] 選議員變選妃！陳柏惟…"
        ],
        [
            "2/07",
            "[新聞] 快訊／陳柏惟被爆包庇…"
        ]
    ],
    "s7503228": [
        [
            "2/07",
            "[新聞] 金門縣議會2次級團體成…"
        ]
    ],
    "gerund": [
        [
            "2/07",
            "[討論] 中國共產黨只有一招能…"
        ]
    ],
    "loser1": [
        [
            "2/07",
            "R: [討論] 中國共產黨只有一招能…"
        ],
        [
            "2/07",
            "R: [討論] 徐巧芯對敵國政權的見解"
        ]
    ],
    "Machinator": [
        [
            "2/07",
            "R: [討論] 覺青生活很淫亂嗎"
        ]
    ],
    "TheoEpstein": [
        [
            "2/07",
            "[討論] 柯粉是不是都捨不得花…"
        ]
    ],
    "miler22020": [
        [
            "2/07",
            "[討論] 快訊 邱莉莉遭到停權三年"
        ]
    ],
    "sdhpipt": [
        [
            "2/07",
            "R: [討論] 有人還記得金美齡這個…"
        ]
    ],
    "tony121010": [
        [
            "2/07",
            "[討論] 國民黨要國軍全面撤出…"
        ]
    ],
    "currry": [
        [
            "2/07",
            "[討論] 數位發展部立委認證技…"
        ]
    ],
    "previa": [
        [
            "2/07",
            "R: [討論] 中國共產黨只有一招能…"
        ]
    ],
    "mimi1020b": [
        [
            "2/07",
            "[討論] 12億的球場 可以抗震芮…"
        ],
        [
            "2/07",
            "[討論] 政治人物都是包裝出來…"
        ]
    ],
    "vava5566": [
        [
            "2/07",
            "R: [討論] 陳柏惟跟陳玄曄長得好像"
        ],
        [
            "2/07",
            "[討論] 抗中保台到現在是不是…"
        ]
    ],
    "oscarwu3041": [
        [
            "2/07",
            "[討論] 韓國瑜初選會支持誰？"
        ]
    ],
    "poter3388": [
        [
            "2/07",
            "[轉錄] 王鴻薇嗆陳時奮該下車了"
        ]
    ],
    "luciffar": [
        [
            "2/07",
            "[黑特] 加入塔利班真的有72位…"
        ]
    ],
    "remora": [
        [
            "2/07",
            "[新聞] 賴清德不捨弔唁星雲法…"
        ]
    ],
    "ihaveseven": [
        [
            "2/07",
            "[討論] 會因為民進黨內高層廢…"
        ]
    ],
    "elfish123": [
        [
            "2/07",
            "[討論] 真的有陳柏惟粉嗎？"
        ]
    ],
    "sincsnow": [
        [
            "2/07",
            "[新聞] 羅智強選那一區的立委好?"
        ]
    ],
    "outdowave": [
        [
            "2/07",
            "[新聞] 陳玄曄遭控渣男劈腿騙…"
        ]
    ],
    "obey1110": [
        [
            "2/07",
            "[討論] 柯文哲民眾黨要起飛了嗎?"
        ]
    ],
    "waitrop": [
        [
            "2/07",
            "R: [黑特] 吃個滷肉飯體會到何謂…"
        ]
    ],
    "wfelix": [
        [
            "2/07",
            "R: [新聞] 同黨秦慧珠嗆「喜歡亂…"
        ]
    ],
    "wwl0909": [
        [
            "2/07",
            "[討論] 民進黨性別平等事務部…"
        ],
        [
            "2/07",
            "[討論] 基粉們一人講一個支持…"
        ]
    ],
    "joe255118": [
        [
            "2/07",
            "[討論] 徐巧芯對敵國政權的見解"
        ]
    ],
    "sean3378": [
        [
            "2/07",
            "R: [黑特] 堂哥陳玄燁:邊棒賽邊回"
        ]
    ],
    "Anderson0819": [
        [
            "2/07",
            "[討論] 論金門非軍事區對台百…"
        ],
        [
            "2/07",
            "[轉錄] 沃草：煩死了，好想要…"
        ]
    ],
    "AGODFATHER": [
        [
            "2/07",
            "R: [討論] 徐巧芯對敵國政權的見解"
        ]
    ],
    "coeXist": [
        [
            "2/07",
            "[討論] 基進現在是在打臉民進…"
        ]
    ],
    "Tosca": [
        [
            "2/07",
            "R: [討論] 論金門非軍事區對台百…"
        ]
    ],
    "bewell": [
        [
            "2/07",
            "R: [黑特] 堂哥陳玄燁:邊棒賽邊回"
        ]
    ],
    "zangetsu9006": [
        [
            "2/07",
            "R: [討論] 中國共產黨只有一招能…"
        ],
        [
            "2/07",
            "R: [討論] 為什麼youtube柯粉比例…"
        ],
        [
            "2/07",
            "R: [新聞] 雞蛋傳將漲3元？陳吉仲…"
        ]
    ],
    "monarch0301": [
        [
            "2/07",
            "[討論] 公有地開放設置攤販怎…"
        ]
    ],
    "qq204": [
        [
            "2/07",
            "[新聞] 民進黨中評會祭最重處…"
        ]
    ],
    "kaminari22tw": [
        [
            "2/07",
            "[新聞] 「交通十八層地獄」是…"
        ]
    ],
    "ke0119": [
        [
            "2/07",
            "R: [討論] 徐巧芯對敵國政權的見解"
        ]
    ],
    "ent661205": [
        [
            "2/07",
            "[討論] 法律國考問題 台灣人去…"
        ],
        [
            "2/07",
            "[討論] 國考刑法 妨害性自主 …"
        ]
    ],
    "jerrylin": [
        [
            "2/07",
            "R: [新聞] 黑道未必叛國！沈伯洋…"
        ],
        [
            "2/07",
            "R: [討論] 徐巧芯對敵國政權的見解"
        ]
    ],
    "boyo": [
        [
            "2/07",
            "R: [討論] 側翼現在最討厭的人是…"
        ]
    ],
    "linx210145": [
        [
            "2/07",
            "[討論] 處男加入基進黨還來得…"
        ],
        [
            "2/07",
            "[討論] 同個環境,時間可以一次…"
        ]
    ],
    "gve50714": [
        [
            "2/07",
            "[討論] 為什麼陳玄曄這型會有…"
        ]
    ],
    "Manzini": [
        [
            "2/07",
            "[討論] 最近台北市的房價狂飆…"
        ]
    ],
    "Lailungsheng": [
        [
            "2/07",
            "R: [討論] 處男加入基進黨還來得…"
        ]
    ],
    "freertos": [
        [
            "2/07",
            "[討論] 智堅 還是請你要倔強 P…"
        ],
        [
            "2/07",
            "[討論] 智堅 是一路走來 始終…"
        ],
        [
            "2/07",
            "[討論] 追小智堅的影片. 小智…"
        ]
    ],
    "shipping5566": [
        [
            "2/07",
            "[討論] 少子化原因"
        ]
    ],
    "syearth": [
        [
            "2/07",
            "[黑特] 忽然了解會投基進黨的…"
        ]
    ],
    "wang19980531": [
        [
            "2/07",
            "[討論] 若不開除林智堅 賴清德…"
        ]
    ],
    "MoneyMonkey": [
        [
            "2/07",
            "R: [討論] 論金門非軍事區對台百…"
        ]
    ],
    "ReeJan": [
        [
            "2/07",
            "R: [討論] 徐巧芯對敵國政權的見解"
        ]
    ],
    "kmter5566": [
        [
            "2/07",
            "[討論] 覺青做愛喊四個堅持有…"
        ]
    ],
    "zhtw": [
        [
            "2/07",
            "R: [討論] 陳柏惟為啥要替堂哥私了"
        ]
    ],
    "kiuyeah": [
        [
            "2/07",
            "[討論] 台灣還沒開放港澳自由…"
        ]
    ],
    "eric2016": [
        [
            "2/07",
            "[黑特] 台派覺青嬉皮政治所衍…"
        ]
    ],
    "dragonjj": [
        [
            "2/07",
            "R: [討論] 龍二你太狠了..."
        ]
    ],
    "kamelot": [
        [
            "2/07",
            "[討論] 林智堅的小編放假這麼…"
        ]
    ],
    "pchunters": [
        [
            "2/07",
            "[新聞] 美國不救我們救! 遇強…"
        ],
        [
            "2/07",
            "[新聞] 公布新會期優先法案 時…"
        ],
        [
            "2/07",
            "[新聞] 南部水情嚴峻 蔡英文呼…"
        ]
    ],
    "kusowan": [
        [
            "2/07",
            "[討論] 女性綠粉是不是都挺慘的"
        ],
        [
            "2/07",
            "[討論] 3Q在泣好像有帶狀節目?"
        ]
    ],
    "Ophiuchus": [
        [
            "2/07",
            "[討論] 民進黨受管制處長出境 …"
        ]
    ],
    "kerorobear": [
        [
            "2/07",
            "[討論] 抗中保台贏過可蘭經嗎？"
        ]
    ],
    "heinse": [
        [
            "2/07",
            "[新聞] 夏立言8日訪陸　朱立倫…"
        ],
        [
            "2/07",
            "[新聞] 王金平：郭台銘回台後…"
        ],
        [
            "2/07",
            "[新聞] 台大副教授駕車遇球棒…"
        ]
    ],
    "takuminauki": [
        [
            "2/07",
            "[討論] 兩大深藍大人物接連過世"
        ]
    ],
    "blessbless": [
        [
            "2/07",
            "[討論] 星雲法師挺國民黨其實…"
        ]
    ],
    "gn7722": [
        [
            "2/07",
            "[討論] 為啥大腸花男男女女渣…"
        ]
    ],
    "moslaa": [
        [
            "2/07",
            "R: [討論] 星雲法師挺國民黨其實…"
        ]
    ],
    "lupin2401": [
        [
            "2/07",
            "[討論] 怎麼有勇氣中出六個女人"
        ]
    ],
    "Fallenshit": [
        [
            "2/07",
            "[討論] 陳玄曄打完砲會說3Q嗎？"
        ]
    ],
    "trf835rea": [
        [
            "2/07",
            "R: [討論] 吳欣岱的臉書到底在講…"
        ]
    ],
    "shun01": [
        [
            "2/07",
            "R: [新聞] 法律竟不允許她選花蓮…"
        ]
    ],
    "sorrows": [
        [
            "2/07",
            "R: [新聞] 管中閔憶台大校長遴選…"
        ]
    ],
    "zo6al": [
        [
            "2/07",
            "[討論] 郭正亮：賴清德會開除…"
        ]
    ]
}