{
    "chinkedout20": [
        [
            "8/19",
            "[徵求] 威秀電影票"
        ]
    ],
    "p4832": [
        [
            "8/19",
            "竹北火車站週邊拾獲鑰匙一串"
        ]
    ],
    "dreambebe": [
        [
            "8/19",
            "[問題] 丹田炙中醫"
        ]
    ],
    "wei76422": [
        [
            "8/19",
            "[贈送] 網購包裝泡棉一大箱"
        ]
    ],
    "mdmmd": [
        [
            "8/19",
            "[徵求] 動茲券 6折收"
        ]
    ],
    "mikiyaki": [
        [
            "8/19",
            "[贈送] Wacom CTE450"
        ]
    ],
    "ioritk": [
        [
            "8/19",
            "[贈送]狗狗雜物贈送"
        ]
    ],
    "xiaolin70181": [
        [
            "8/19",
            "[徵求] 配電用PF管 10米/防日曬收納管"
        ]
    ],
    "QQqueen": [
        [
            "8/19",
            "[徵求] 新竹飛秒近視雷射手術團報"
        ]
    ],
    "budda": [
        [
            "8/19",
            "[贈送] 健身車"
        ]
    ],
    "luckytinasui": [
        [
            "8/19",
            "[贈送] 即期營養蛋白及吹風機"
        ]
    ],
    "Bergling": [
        [
            "8/19",
            "[徵求] 魚雷浮標"
        ]
    ],
    "ANIO1021": [
        [
            "8/19",
            "[徵求] 最近有想買3C的人~50000以內"
        ]
    ],
    "MusicLo": [
        [
            "8/19",
            "[贈送] 竹北贈送貓罐頭170g 20罐"
        ]
    ],
    "smilekelsy": [
        [
            "8/19",
            "[贈送] 女寶0-6M冬裝/9-18M冬裝/9-1…"
        ]
    ],
    "vicekid": [
        [
            "8/19",
            "[贈送] Lancer fortis原廠音響面板"
        ]
    ],
    "jyjyl": [
        [
            "8/19",
            "[問題] 竹北有推薦修ipad的店家嗎？"
        ]
    ],
    "goodcutecat": [
        [
            "8/19",
            "Fw: [情報] 新竹 國賓大飯店: 五星商務…"
        ]
    ],
    "lilittlefox": [
        [
            "8/19",
            "[徵求] WG竹北會員"
        ]
    ],
    "sam91305": [
        [
            "8/19",
            "[徵求] 二手電風扇"
        ]
    ],
    "pinky033": [
        [
            "8/19",
            "[協尋] 新竹市走失橘白母貓"
        ]
    ],
    "shipinRD": [
        [
            "8/19",
            "[問題] 園區在塞什麼"
        ]
    ],
    "fftt1008": [
        [
            "8/19",
            "[贈送] 二手女生英文童書"
        ],
        [
            "8/19",
            "[贈送] 9.9新 富士電通1.0L除濕機"
        ]
    ],
    "mr844332": [
        [
            "8/19",
            "[徵求] IKEA 點食成金 200NT抵用劵"
        ]
    ],
    "Petyr": [
        [
            "8/19",
            "[問題] 新竹哪邊有在收超大紙箱"
        ]
    ],
    "skyHuan": [
        [
            "8/19",
            "[贈送] 烤肉食材 豬肉&花枝丸"
        ]
    ],
    "HUSKY13": [
        [
            "8/19",
            "新竹大同路拾獲信用卡一張"
        ]
    ],
    "sya": [
        [
            "8/19",
            "[贈送] 雜物小物"
        ]
    ],
    "SRT0619": [
        [
            "8/19",
            "[贈送] 德恩奈漱口水 500ml x4"
        ]
    ],
    "pttccpcman": [
        [
            "8/19",
            "[問題] 跳電？"
        ]
    ]
}